MANIFEST.in
README.md
requirements.txt
setup.py
api_toolkit/__init__.py
api_toolkit/entities.py
api_toolkit.egg-info/PKG-INFO
api_toolkit.egg-info/SOURCES.txt
api_toolkit.egg-info/dependency_links.txt
api_toolkit.egg-info/requires.txt
api_toolkit.egg-info/top_level.txt
api_toolkit/tests/__init__.py
api_toolkit/tests/helpers.py
api_toolkit/tests/test_entities.py
api_toolkit/tests/cassettes/charge_account/all
api_toolkit/tests/cassettes/charge_account/create
api_toolkit/tests/cassettes/charge_account/create_with_location
api_toolkit/tests/cassettes/charge_account/create_with_returned_data
api_toolkit/tests/cassettes/charge_account/delete
api_toolkit/tests/cassettes/charge_account/get
api_toolkit/tests/cassettes/charge_account/save
api_toolkit/tests/cassettes/charge_account/to_be_deleted
api_toolkit/tests/cassettes/domain/load
api_toolkit/tests/cassettes/domain/wrong