Metadata-Version: 1.1
Name: api-toolkit
Version: 0.3.5
Summary: A library which simplifies the creation of clients for REST webservices.
Home-page: http://github.com/myfreecomm/python-api-toolkit
Author: vitormazzi
Author-email: vitormazzi@gmail.com
License: Apache 2.0
Keywords: python rest webservices
Platform: UNKNOWN
Classifier: Intended Audience :: Developers
Classifier: License :: OSI Approved :: Apache Software License
Classifier: Operating System :: OS Independent
Classifier: Topic :: Software Development
